README.md
setup.py
stress/__init__.py
stress/stress.py
stress.egg-info/PKG-INFO
stress.egg-info/SOURCES.txt
stress.egg-info/dependency_links.txt
stress.egg-info/entry_points.txt
stress.egg-info/requires.txt
stress.egg-info/top_level.txt